radexwrap.cpython-310-darwin.so
spectralradex/version.py
spectralradex/__init__.py
spectralradex/radex/__init__.py
spectralradex/radex/data/hcn.dat
spectralradex/radex/data/c+.dat
spectralradex/radex/data/hcl@hfs.dat
spectralradex/radex/data/hcl.dat
spectralradex/radex/data/oh.dat
spectralradex/radex/data/co.dat
spectralradex/radex/data/p-nh3.dat
spectralradex/radex/data/ch2_h2_ortho.dat
spectralradex/radex/data/oh+.dat
spectralradex/radex/data/n+.dat
spectralradex/radex/data/catom.dat
spectralradex/radex/data/ch2_h2_para.dat
spectralradex/radex/data/sio.dat
spectralradex/radex/data/oh2s.dat
spectralradex/radex/data/o-nh3.dat
spectralradex/radex/data/hcn@hfs.dat
spectralradex/radex/data/hd.dat
spectralradex/radex/data/hco+.dat
spectralradex/radex/data/o-h3o+.dat
spectralradex/radex/data/ph2s.dat
spectralradex/radex/data/p-h3o+.dat
spectralradex/radex/data/ph2cs.dat
spectralradex/radex/data/o-sic2.dat
spectralradex/radex/data/SO-pH2.dat
spectralradex/radex/data/hc3n.dat
spectralradex/radex/data/so2@lowT.dat
spectralradex/radex/data/oatom.dat
spectralradex/radex/data/hnc.dat
spectralradex/radex/data/o-c3h2.dat
spectralradex/radex/data/cs@lique.dat
spectralradex/radex/data/p-c3h2.dat
spectralradex/radex/data/oh@hfs.dat
spectralradex/radex/data/o2.dat
spectralradex/radex/data/oh2cs.dat
spectralradex/.dylibs/libgfortran.5.dylib
spectralradex/.dylibs/libquadmath.0.dylib
spectralradex/.dylibs/libgcc_s.1.1.dylib
spectralradex-1.1.5.dist-info/RECORD
spectralradex-1.1.5.dist-info/LICENSE
spectralradex-1.1.5.dist-info/WHEEL
spectralradex-1.1.5.dist-info/top_level.txt
spectralradex-1.1.5.dist-info/METADATA
