Metadata-Version: 2.1
Name: spectralradex
Version: 1.1.5
Summary: A package for RADEX and spectral modelling
Home-page: https://spectralradex.readthedocs.io
Author: Jonathan Holdship
Author-email: jonholdship@gmail.com
Classifier: Development Status :: 5 - Production/Stable
Classifier: Programming Language :: Python :: 3
Classifier: License :: OSI Approved :: MIT License
Classifier: Operating System :: OS Independent
Requires-Python: >=3.6
License-File: LICENSE
Requires-Dist: pandas
Requires-Dist: numpy
